acmecse/__init__.py
acmecse/__main__.py
acmecse/databases/DBBinding.py
acmecse/databases/PostgreSQLBinding.py
acmecse/databases/TinyDBBinding.py
acmecse/databases/__init__.py
acmecse/etc/ACMEUtils.py
acmecse/etc/Constants.py
acmecse/etc/DateUtils.py
acmecse/etc/GeoTools.py
acmecse/etc/RequestUtils.py
acmecse/etc/ResponseStatusCodes.py
acmecse/etc/Types.py
acmecse/etc/Utils.py
acmecse/etc/__init__.py
acmecse/helpers/ACMEIntEnum.py
acmecse/helpers/BackgroundWorker.py
acmecse/helpers/CoapDissector.py
acmecse/helpers/EventManager.py
acmecse/helpers/Interpreter.py
acmecse/helpers/KeyHandler.py
acmecse/helpers/MQTTConnection.py
acmecse/helpers/NetworkTools.py
acmecse/helpers/OAuth.py
acmecse/helpers/OrderedSet.py
acmecse/helpers/ReadWriteLock.py
acmecse/helpers/ResourceSemaphore.py
acmecse/helpers/TextTools.py
acmecse/helpers/ThreadSafeCounter.py
acmecse/helpers/TinyDBBetterTable.py
acmecse/helpers/TinyDBBufferedStorage.py
acmecse/helpers/UDPServer.py
acmecse/helpers/__init__.py
acmecse/init/ASFunctions.as
acmecse/init/acme.ini.default
acmecse/init/action.as_
acmecse/init/action2.as
acmecse/init/action3.as_
acmecse/init/agd-dev.fcp
acmecse/init/agd-mc.fcp
acmecse/init/attributePolicies.ap
acmecse/init/attributePolicies.fcp
acmecse/init/bla.as
acmecse/init/cid-dev.fcp
acmecse/init/cod-dev.fcp
acmecse/init/cod-mc.fcp
acmecse/init/cod-sdev.fcp
acmecse/init/complexTypePolicies.ap
acmecse/init/configurations.docmd
acmecse/init/covid.fcp
acmecse/init/curve.as
acmecse/init/enumTypesPolicies.ep
acmecse/init/getConfigurationUT.as
acmecse/init/hed-dev.fcp
acmecse/init/hed-mc.fcp
acmecse/init/hed-sdev.fcp
acmecse/init/hod-dev.fcp
acmecse/init/hod-mc.fcp
acmecse/init/ind-dev.fcp
acmecse/init/ind-mc.fcp
acmecse/init/init.as
acmecse/init/iotOrchestrator.fcp
acmecse/init/mad-dev.fcp
acmecse/init/mad-mc.fcp
acmecse/init/mad-sdev.fcp
acmecse/init/mdd-mc.fcp
acmecse/init/melodyImperial.as
acmecse/init/melodyTheme.as
acmecse/init/psd-dev.fcp
acmecse/init/psd-mc.fcp
acmecse/init/query.as
acmecse_test-2024.5.dist-info/LICENSE
acmecse_test-2024.5.dist-info/METADATA
acmecse_test-2024.5.dist-info/WHEEL
acmecse_test-2024.5.dist-info/entry_points.txt
acmecse_test-2024.5.dist-info/top_level.txt
acmecse_test-2024.5.dist-info/RECORD
