Metadata-Version: 2.1
Name: acmecse-test
Version: 2024.5
Summary: An open source CSE Middleware for Education
Home-page: https://github.com/ankraft/ACME-oneM2M-CSE
Author: Andreas Kraft
Author-email: an.kraft@gmail.com
License: BSD
Classifier: License :: OSI Approved :: BSD License
Classifier: Programming Language :: Python :: 3.10
License-File: LICENSE
Requires-Dist: cbor2
Requires-Dist: flask
Requires-Dist: flask-cors
Requires-Dist: InquirerPy
Requires-Dist: isodate
Requires-Dist: paho-mqtt >=2.0.0
Requires-Dist: plotext
Requires-Dist: psycopg2-binary
Requires-Dist: python3-dtls
Requires-Dist: rdflib
Requires-Dist: requests
Requires-Dist: rich
Requires-Dist: shapely
Requires-Dist: textual
Requires-Dist: textual-plotext
Requires-Dist: tinydb
Requires-Dist: waitress
Requires-Dist: websockets
